LICENSE.rst
README.md
setup.cfg
setup.py
src/chargily_epay_gateway/__init__.py
src/chargily_epay_gateway/api.py
src/chargily_epay_gateway/constants.py
src/chargily_epay_gateway/exceptions.py
src/chargily_epay_gateway/security.py
src/chargily_epay_gateway/utils.py
src/chargily_epay_gateway.egg-info/PKG-INFO
src/chargily_epay_gateway.egg-info/SOURCES.txt
src/chargily_epay_gateway.egg-info/dependency_links.txt
src/chargily_epay_gateway.egg-info/requires.txt
src/chargily_epay_gateway.egg-info/top_level.txt