Metadata-Version: 2.1
Name: chargily-epay-gateway
Version: 0.2
Summary: UNKNOWN
Home-page: https://github.com/Chargily/epay-gateway-python
Author: Chargily
Author-email: chargily@gmail.com
License: MIT
Project-URL: Global Website, https://chargily.com
Project-URL: DZ Website, https://chargily.com.dz
Project-URL: Github, https://github.com/Chargily/epay-gateway-python
Keywords: chargily,e-payment,integration,python
Platform: UNKNOWN
License-File: LICENSE.rst
